fritzxhr.py
fritzxhr-0.1.0.dist-info/LICENSE
fritzxhr-0.1.0.dist-info/WHEEL
fritzxhr-0.1.0.dist-info/METADATA
fritzxhr-0.1.0.dist-info/RECORD
