Metadata-Version: 2.1
Name: fritzxhr
Version: 0.1.0
Summary: An interface to FRITZ!Box web settings
License: MIT
Author: Andreas Oberritter
Author-email: obi@saftware.de
Requires-Python: >=3.6,<4.0
Classifier: License :: OSI Approved :: MIT License
Classifier: Programming Language :: Python :: 3
Classifier: Programming Language :: Python :: 3.10
Classifier: Programming Language :: Python :: 3.6
Classifier: Programming Language :: Python :: 3.7
Classifier: Programming Language :: Python :: 3.8
Classifier: Programming Language :: Python :: 3.9
Requires-Dist: defusedxml (>=0.7.1,<0.8.0)
Requires-Dist: requests (>=2.27.1,<3.0.0)
